WB/design.sv
// Code your design here
//`timescale 1ns/1ps

module Wishbone_master (
  input wire clk,
  input wire rst,

  // Wishbone Interface
  output reg wb_cyc_o,
  output reg wb_stb_o,
  output reg wb_we_o,
  output reg [31:0] wb_adr_o,
  output reg [31:0] wb_dat_o,

  input wire [31:0] wb_dat_i,
  input wire wb_ack_i,

  // FIFO Interface
  input wire fifo_read_en,
  input wire fifo_write_en,
  input wire fifo_empty,
  input wire [31:0] fifo_data_in,

  output reg [31:0] fifo_data_out
);

  // FSM States
  reg [2:0] state;
  reg [2:0] next_state;

  // State Definitions
  localparam IDLE       = 3'b000;
  localparam READ_REQ   = 3'b001;
  localparam READ_RESP  = 3'b010;
  localparam WRITE_REQ  = 3'b011;
  localparam WRITE_RESP = 3'b100;

  // FSM State Transitions
  always @(posedge clk or posedge rst) begin
    if (rst == 1'b1) begin
      state <= IDLE;
    end else begin
      state <= next_state;
    end
  end

  // FSM Next State Logic and Outputs
  always @(*) begin
    next_state = state;
    
    case (state)
      IDLE: begin
        wb_cyc_o = 0;
    	wb_stb_o = 0;       
        
        if (fifo_read_en && !fifo_empty) begin
          next_state = READ_REQ;
        end else if (fifo_write_en && !fifo_empty)
          next_state = WRITE_REQ;
      end

      READ_REQ: begin
        wb_cyc_o = 1;
        wb_stb_o = 1;
        wb_we_o = 0;  // Read operation
        wb_adr_o = fifo_data_in;

        next_state = READ_RESP;
      end

      READ_RESP: begin

        if (wb_ack_i) begin
          fifo_data_out = wb_dat_i;
          next_state = IDLE;
        end
      end

      WRITE_REQ: begin
        wb_cyc_o = 1;
        wb_stb_o = 1;
        wb_we_o = 1;  // Write operation  

        next_state = WRITE_RESP;
      end

      WRITE_RESP: begin

        if (wb_ack_i) begin
          next_state = IDLE;
        end
      end

      default: begin
        next_state = IDLE;
      end
    endcase
  end

endmodule

WB/tb1.v
module tb_Wishbone_master();

    // Clock and reset
    reg clk;
    reg rst;

    // Wishbone signals
    wire wb_cyc_o;
    wire wb_stb_o;
    wire wb_we_o;
    wire [31:0] wb_adr_o;
    wire [31:0] wb_dat_o;
    reg [31:0] wb_dat_i;
    reg wb_ack_i;

    // FIFO signals
    reg fifo_read_en;
    reg fifo_write_en;
    reg fifo_empty;
    reg [31:0] fifo_data_in;
    wire [31:0] fifo_data_out;

    Wishbone_master uut (
        .clk(clk),
        .rst(rst),
        .wb_cyc_o(wb_cyc_o),
        .wb_stb_o(wb_stb_o),
        .wb_we_o(wb_we_o),
        .wb_adr_o(wb_adr_o),
        .wb_dat_o(wb_dat_o),
        .wb_dat_i(wb_dat_i),
        .wb_ack_i(wb_ack_i),
        .fifo_read_en(fifo_read_en),
        .fifo_write_en(fifo_write_en),
        .fifo_empty(fifo_empty),
        .fifo_data_in(fifo_data_in),
        .fifo_data_out(fifo_data_out)
    );

    // Clock
    initial begin
        clk = 0;
        forever #10 clk = ~clk;
    end
  
	initial begin
      $dumpfile("waveform.vcd");
      $dumpvars(0, tb_Wishbone_master);
    end
  
    // Testbench
    initial begin
      rst = 1;
      fifo_read_en = 0;
      fifo_write_en = 0;
      fifo_empty = 1;
      fifo_data_in = 0;
      wb_dat_i = 0;
      wb_ack_i = 0;

      
        
    end 

endmodule

WB/waveform.vcd
$date
	Mon Sep  9 00:25:05 2024
$end
$version
	Icarus Verilog
$end
$timescale
	1s
$end
$scope module tb_Wishbone_master $end
$var wire 1 ! wb_we_o $end
$var wire 1 " wb_stb_o $end
$var wire 32 # wb_dat_o [31:0] $end
$var wire 1 $ wb_cyc_o $end
$var wire 32 % wb_adr_o [31:0] $end
$var wire 32 & fifo_data_out [31:0] $end
$var reg 1 ' clk $end
$var reg 32 ( fifo_data_in [31:0] $end
$var reg 1 ) fifo_empty $end
$var reg 1 * fifo_read_en $end
$var reg 1 + fifo_write_en $end
$var reg 1 , rst $end
$var reg 1 - wb_ack_i $end
$var reg 32 . wb_dat_i [31:0] $end
$scope module uut $end
$var wire 1 ' clk $end
$var wire 32 / fifo_data_in [31:0] $end
$var wire 1 ) fifo_empty $end
$var wire 1 * fifo_read_en $end
$var wire 1 + fifo_write_en $end
$var wire 1 , rst $end
$var wire 1 - wb_ack_i $end
$var wire 32 0 wb_dat_i [31:0] $end
$var parameter 3 1 IDLE $end
$var parameter 3 2 READ_REQ $end
$var parameter 3 3 READ_RESP $end
$var parameter 3 4 WRITE_REQ $end
$var parameter 3 5 WRITE_RESP $end
$var reg 32 6 fifo_data_out [31:0] $end
$var reg 3 7 next_state [2:0] $end
$var reg 3 8 state [2:0] $end
$var reg 32 9 wb_adr_o [31:0] $end
$var reg 1 $ wb_cyc_o $end
$var reg 32 : wb_dat_o [31:0] $end
$var reg 1 " wb_stb_o $end
$var reg 1 ! wb_we_o $end
$upscope $end
$upscope $end
$enddefinitions $end
$comment Show the parameter values. $end
$dumpall
b100 5
b11 4
b10 3
b1 2
b0 1
$end
#0
$dumpvars
bx :
bx 9
b0 8
b0 7
bx 6
b0 0
b0 /
b0 .
0-
1,
0+
0*
1)
b0 (
0'
bx &
bx %
0$
bx #
0"
0!
$end
#10
0,
1'
#20
b1 7
b11010001010100011101001001010 (
b11010001010100011101001001010 /
0)
1*
0'
#30
b10 7
b11010001010100011101001001010 %
b11010001010100011101001001010 9
1"
1$
b1 8
1'
#40
0'
#50
b11111111111111111111111111111111 &
b11111111111111111111111111111111 6
b10 8
b0 7
1-
b11111111111111111111111111111111 .
b11111111111111111111111111111111 0
1'
#60
0'
#70
0*
0"
0$
b0 8
b0 7
0-
1'
#80
0'
#90
1'
#100
0'
#110
1'
#120
0'
1,
#130
1'
0,
#140
0'
#150
b11011001010110011101101001011 %
b11011001010110011101101001011 9
1!
1"
1$
b11 8
b11 7
1'
b11011001010110011101101001011 (
b11011001010110011101101001011 /
1+
#160
b100 7
0'
1-
#170
b0 7
b11011001010110011101101001011 #
b11011001010110011101101001011 :
b100 8
1'
#180
0'
#190
0-
0+
0!
0"
0$
b0 8
b11101110111011101110111011101110 #
b11101110111011101110111011101110 :
b0 7
1'
b11101110111011101110111011101110 (
b11101110111011101110111011101110 /
